infiltrator/__init__.py
infiltrator/__main__.py
infiltrator/cli.py
infiltrator/config_wizard.py
infiltrator/main.py
infiltrator/core/__init__.py
infiltrator/core/adapter_manager.py
infiltrator/core/banner.py
infiltrator/core/config.py
infiltrator/core/logger.py
infiltrator/core/menu.py
infiltrator/modules/__init__.py
infiltrator/modules/exploitation.py
infiltrator/modules/post_attack.py
infiltrator/modules/reconnaissance.py
infiltrator_wifi-1.0.1.dist-info/LICENSE.md
infiltrator_wifi-1.0.1.dist-info/METADATA
infiltrator_wifi-1.0.1.dist-info/WHEEL
infiltrator_wifi-1.0.1.dist-info/entry_points.txt
infiltrator_wifi-1.0.1.dist-info/top_level.txt
infiltrator_wifi-1.0.1.dist-info/RECORD
