Metadata-Version: 2.1
Name: infiltrator-wifi
Version: 1.0.1
Summary: WiFi Red Team Auditing Suite - Professional penetration testing framework
Home-page: https://github.com/letchupkt/infiltrator
Author: LAKSHMIKANTHAN K
Author-email: LAKSHMIKANTHAN K <letchupkt@example.com>
Maintainer-email: LAKSHMIKANTHAN K <letchupkt@example.com>
License: MIT
Project-URL: Homepage, https://github.com/letchupkt/infiltrator
Project-URL: Documentation, https://github.com/letchupkt/infiltrator#readme
Project-URL: Repository, https://github.com/letchupkt/infiltrator
Project-URL: Bug Tracker, https://github.com/letchupkt/infiltrator/issues
Keywords: wifi,security,penetration-testing,red-team,wireless,hacking
Platform: Linux
Classifier: Development Status :: 5 - Production/Stable
Classifier: Intended Audience :: Information Technology
Classifier: Intended Audience :: System Administrators
Classifier: Topic :: Security
Classifier: Topic :: System :: Networking
Classifier: License :: OSI Approved :: MIT License
Classifier: Programming Language :: Python :: 3
Classifier: Programming Language :: Python :: 3.8
Classifier: Programming Language :: Python :: 3.9
Classifier: Programming Language :: Python :: 3.10
Classifier: Programming Language :: Python :: 3.11
Classifier: Operating System :: POSIX :: Linux
Classifier: Environment :: Console
Requires-Python: >=3.8
License-File: LICENSE.md
Requires-Dist: colorama>=0.4.6
Requires-Dist: python-dateutil>=2.8.2
Requires-Dist: requests>=2.31.0
Requires-Dist: tabulate>=0.9.0
Provides-Extra: dev
Requires-Dist: pytest; extra == "dev"
Requires-Dist: black; extra == "dev"
Requires-Dist: flake8; extra == "dev"
Requires-Dist: mypy; extra == "dev"
Provides-Extra: gps
Requires-Dist: gps3>=0.33.3; extra == "gps"
Requires-Dist: gpsd-py3>=0.3.0; extra == "gps"
